setup.py
message_server_zda.egg-info/PKG-INFO
message_server_zda.egg-info/SOURCES.txt
message_server_zda.egg-info/dependency_links.txt
message_server_zda.egg-info/requires.txt
message_server_zda.egg-info/top_level.txt
server/__init__.py
server/server.py
server/apr_doc/__init__.py
server/apr_doc/source/__init__.py
server/apr_doc/source/conf.py
server/common/__init__.py
server/common/decor.py
server/common/descriptrs.py
server/common/metaclasses.py
server/common/utils.py
server/common/variables.py
server/log/__init__.py
server/log/configs/__init__.py
server/log/configs/client_log_config.py
server/log/configs/server_log_config.py
server/server/__init__.py
server/server/add_user.py
server/server/config_window.py
server/server/core.py
server/server/main_window.py
server/server/remove_user.py
server/server/server_database.py
server/server/stat_window.py